{"portalId":2277117,"dealId":49284703,"isDeleted":false,"associations":{"associatedVids":[],"associatedCompanyIds":[219060674],"associatedDealIds":[]},"properties":{"dealname":{"value":"Kavat - FlowTarget XS","timestamp":1475667576462,"source":"CRM_UI","sourceId":"gustav.rosen@entiros.se","versions":[{"name":"dealname","value":"Kavat - FlowTarget XS","timestamp":1475667576462,"sourceId":"gustav.rosen@entiros.se","source":"CRM_UI","sourceVid":[]}]},"notes_last_updated":{"value":"1500884402611","timestamp":1500884403246,"source":"ENGAGEMENTS","sourceId":"ObjectPropertyUpdater","versions":[{"name":"notes_last_updated","value":"1500884402611","timestamp":1500884403246,"sourceId":"ObjectPropertyUpdater","source":"ENGAGEMENTS","sourceVid":[]}]},"amount":{"value":"10000","timestamp":1475667558540,"source":"CRM_UI","sourceId":"gustav.rosen@entiros.se","versions":[{"name":"amount","value":"10000","timestamp":1475667558540,"sourceId":"gustav.rosen@entiros.se","source":"CRM_UI","sourceVid":[]}]},"closed_lost_reason":{"value":"","timestamp":1493905081223,"source":"CRM_UI","sourceId":"nils.kanevad@entiros.se","versions":[{"name":"closed_lost_reason","timestamp":1493905081223,"sourceId":"nils.kanevad@entiros.se","source":"CRM_UI","sourceVid":[]}]},"closedate":{"value":"1493905079539","timestamp":1493905081223,"source":"CRM_UI","sourceId":"nils.kanevad@entiros.se","versions":[{"name":"closedate","value":"1493905079539","timestamp":1493905081223,"sourceId":"nils.kanevad@entiros.se","source":"CRM_UI","sourceVid":[]}]},"num_associated_contacts":{"value":"0","timestamp":0,"source":"CALCULATED","sourceId":null,"versions":[{"name":"num_associated_contacts","value":"0","source":"CALCULATED","sourceVid":[]}]},"createdate":{"value":"1471333848689","timestamp":1471333848689,"source":"SALES","sourceId":"CRM_UI","versions":[{"name":"createdate","value":"1471333848689","timestamp":1471333848689,"sourceId":"CRM_UI","source":"SALES","sourceVid":[]}]},"engagements_last_meeting_booked":{"value":"","timestamp":1481019717748,"source":"ENGAGEMENTS","sourceId":"DealsBatchMutation","versions":[{"name":"engagements_last_meeting_booked","value":"","timestamp":1481019717748,"sourceId":"DealsBatchMutation","source":"ENGAGEMENTS","sourceVid":[]}]},"pipeline":{"value":"default","timestamp":1471333848647,"source":"CRM_UI","sourceId":"gustav.rosen@entiros.se","versions":[{"name":"pipeline","value":"default","timestamp":1471333848647,"sourceId":"gustav.rosen@entiros.se","source":"CRM_UI","sourceVid":[]}]},"hubspot_team_id":{"value":"6575","timestamp":1500884402281,"source":"API","sourceId":"DEALBatchMutationResource","versions":[{"name":"hubspot_team_id","value":"6575","timestamp":1500884402281,"sourceId":"DEALBatchMutationResource","source":"API","sourceVid":[]}]},"hubspot_owner_id":{"value":"11792051","timestamp":1475667494106,"source":"CRM_UI","sourceId":"gustav.rosen@entiros.se","versions":[{"name":"hubspot_owner_id","value":"11792051","timestamp":1475667494106,"sourceId":"gustav.rosen@entiros.se","source":"CRM_UI","sourceVid":[]}]},"hs_analytics_source":{"value":"OFFLINE","timestamp":1487738139744,"source":"CALCULATED","sourceId":"deal sync triggered by company id=219060674","versions":[{"name":"hs_analytics_source","value":"OFFLINE","timestamp":1487738139744,"sourceId":"deal sync triggered by company id=219060674","source":"CALCULATED","sourceVid":[]}]},"hs_lastmodifieddate":{"value":"1500884403494","timestamp":1500884403494,"source":"CALCULATED","sourceId":null,"versions":[{"name":"hs_lastmodifieddate","value":"1500884403494","timestamp":1500884403494,"source":"CALCULATED","sourceVid":[]}]},"num_contacted_notes":{"value":"0","timestamp":1471334385419,"source":"ENGAGEMENTS","sourceId":"DealsBatchMutation","versions":[{"name":"num_contacted_notes","value":"0","timestamp":1471334385419,"sourceId":"DealsBatchMutation","source":"ENGAGEMENTS","sourceVid":[]}]},"hubspot_owner_assigneddate":{"value":"1475667494106","timestamp":1475667494106,"source":"CRM_UI","sourceId":"gustav.rosen@entiros.se","versions":[{"name":"hubspot_owner_assigneddate","value":"1475667494106","timestamp":1475667494106,"sourceId":"gustav.rosen@entiros.se","source":"CRM_UI","sourceVid":[]}]},"notes_last_contacted":{"value":"","timestamp":1481019717748,"source":"ENGAGEMENTS","sourceId":"DealsBatchMutation","versions":[{"name":"notes_last_contacted","value":"","timestamp":1481019717748,"sourceId":"DealsBatchMutation","source":"ENGAGEMENTS","sourceVid":[]}]},"dealstage":{"value":"closedlost","timestamp":1493905079358,"source":"CRM_UI","sourceId":"nils.kanevad@entiros.se","versions":[{"name":"dealstage","value":"closedlost","timestamp":1493905079358,"sourceId":"nils.kanevad@entiros.se","source":"CRM_UI","sourceVid":[]}]},"hs_createdate":{"value":"1471333848689","timestamp":1471333848689,"source":"SALES","sourceId":"CRM_UI","versions":[{"name":"hs_createdate","value":"1471333848689","timestamp":1471333848689,"sourceId":"CRM_UI","source":"SALES","sourceVid":[]}]},"hs_analytics_source_data_2":{"value":"CRM_UI","timestamp":1487738139744,"source":"CALCULATED","sourceId":"deal sync triggered by company id=219060674","versions":[{"name":"hs_analytics_source_data_2","value":"CRM_UI","timestamp":1487738139744,"sourceId":"deal sync triggered by company id=219060674","source":"CALCULATED","sourceVid":[]}]},"hs_analytics_source_data_1":{"value":"SALES","timestamp":1487738139744,"source":"CALCULATED","sourceId":"deal sync triggered by company id=219060674","versions":[{"name":"hs_analytics_source_data_1","value":"SALES","timestamp":1487738139744,"sourceId":"deal sync triggered by company id=219060674","source":"CALCULATED","sourceVid":[]}]},"notes_next_activity_date":{"value":"","timestamp":1481019717748,"source":"ENGAGEMENTS","sourceId":"DealsBatchMutation","versions":[{"name":"notes_next_activity_date","value":"","timestamp":1481019717748,"sourceId":"DealsBatchMutation","source":"ENGAGEMENTS","sourceVid":[]}]},"num_notes":{"value":"1","timestamp":1471334385419,"source":"ENGAGEMENTS","sourceId":"DealsBatchMutation","versions":[{"name":"num_notes","value":"1","timestamp":1471334385419,"sourceId":"DealsBatchMutation","source":"ENGAGEMENTS","sourceVid":[]}]}},"imports":[],"stateChanges":[]}