{"person":{"id":32254,"first_name":"Patrik","last_name":"Afzelius","email":"patrik.afzelius@entiros.se","login":"enabled","admin":true,"archived":true,"subscribed":false,"avatar_url":"https://secure.gravatar.com/avatar/88d287efe08853a22feeb54f9af34fce.jpg?s=200\u0026d=https://forecast-files.s3.amazonaws.com/default-avatars/PA.png","teams":["Operations","SS"],"updated_at":"2016-10-07T12:11:24.739Z","updated_by_id":30410,"harvest_user_id":764949,"weekly_capacity":null,"working_days":{"monday":true,"tuesday":true,"wednesday":true,"thursday":true,"friday":true},"color_blind":false}}